customer_purchases/__init__.py
customer_purchases/v1/__init__.py
customer_purchases/v1/data_ana/__init__.py
customer_purchases/v1/data_ana/pipeline.py
customer_purchases/v1/data_sci/__init__.py
customer_purchases/v1/data_sci/pipeline.py
version.py
customer_purchases_final-1.0.0.dist-info/METADATA
customer_purchases_final-1.0.0.dist-info/WHEEL
customer_purchases_final-1.0.0.dist-info/RECORD
