Metadata-Version: 2.3
Name: customer_purchases_final
Version: 1.0.0
Summary: Customer purchases large dataset processing pipeline
License: MIT
Author: Slimane Rhaytou
Requires-Python: >=3.11
Classifier: License :: OSI Approved :: MIT License
Classifier: Programming Language :: Python :: 3
Classifier: Programming Language :: Python :: 3.11
Classifier: Programming Language :: Python :: 3.12
Classifier: Programming Language :: Python :: 3.13
Requires-Dist: numpy (>=2.3.2,<3.0.0)
Requires-Dist: pandas (>=2.3.1,<3.0.0)
Requires-Dist: python-dotenv (>=1.1.1,<2.0.0)
